bustimes/__init__.py
bustimes/bus.py
bustimes/process_data.py
bustimes-1.1.0.dist-info/LICENSE
bustimes-1.1.0.dist-info/METADATA
bustimes-1.1.0.dist-info/WHEEL
bustimes-1.1.0.dist-info/top_level.txt
bustimes-1.1.0.dist-info/RECORD
