Metadata-Version: 2.1
Name: bustimes
Version: 1.1.0
Summary: A simple bus times library
Project-URL: Homepage, https://github.com/TheOctoGirl/bustimes
Project-URL: Bug Tracker, https://github.com/TheOctoGirl/bustimes/issues
Project-URL: Documentation, https://github.com/TheOctoGirl/bustimes/wiki
Classifier: Programming Language :: Python :: 3
Classifier: License :: OSI Approved :: MIT License
Classifier: Operating System :: OS Independent
Requires-Python: >=3.11
License-File: LICENSE
Requires-Dist: requests >=2.31.0
